[
    {
        "symbol": "ETH-USDT",
        "base": "ETH",
        "name": "Ethereum",
        "market_cap": 195121398495,
        "rank": 2,
        "coingecko_id": "ethereum",
        "last_price": "1617.97",
        "volume_24h": "306845.77",
        "funding_rate": "0.00010000",
        "spread_percent": 0.001236216189486093,
        "open_interest": "415920214.70",
        "atr": 12.446428571428555,
        "atr_percent": 0.7755557296321475,
        "orderbook_depth": 15418098.6474,
        "score_funding": 10,
        "score_spread": 10,
        "score_open_interest": 12,
        "score_atr": 7,
        "score_orderbook_depth": 6,
        "score_data_quality": 3,
        "hard_filter_passed": true,
        "hard_filter_reasons": [],
        "score_market_cap": 15,
        "score_rank": 10,
        "score_volume": 3,
        "market_quality_score": 76
    },
    {
        "symbol": "SOL-USDT",
        "base": "SOL",
        "name": "Solana",
        "market_cap": 45071159253,
        "rank": 7,
        "coingecko_id": "solana",
        "last_price": "77.626",
        "volume_24h": "3765897.20",
        "funding_rate": "-0.00010900",
        "spread_percent": 0.012887262230000135,
        "open_interest": "241170368.742",
        "atr": 0.6628571428571429,
        "atr_percent": 0.9105805932511065,
        "orderbook_depth": 4259438.973999999,
        "score_funding": 8,
        "score_spread": 8,
        "score_open_interest": 9,
        "score_atr": 7,
        "score_orderbook_depth": 3,
        "score_data_quality": 3,
        "hard_filter_passed": true,
        "hard_filter_reasons": [],
        "score_market_cap": 13,
        "score_rank": 10,
        "score_volume": 9,
        "market_quality_score": 70
    },
    {
        "symbol": "AVAX-USDT",
        "base": "AVAX",
        "name": "Avalanche",
        "market_cap": 2903782072,
        "rank": 31,
        "coingecko_id": "avalanche-2",
        "last_price": "6.723",
        "volume_24h": "3389759",
        "funding_rate": "0.00010000",
        "spread_percent": 0.029739776951682794,
        "open_interest": "19162197.079",
        "atr": 0.07378571428571419,
        "atr_percent": 1.1124033512093199,
        "orderbook_depth": 15298738.541000001,
        "score_funding": 10,
        "score_spread": 8,
        "score_open_interest": 3,
        "score_atr": 10,
        "score_orderbook_depth": 6,
        "score_data_quality": 3,
        "hard_filter_passed": true,
        "hard_filter_reasons": [],
        "score_market_cap": 8,
        "score_rank": 6,
        "score_volume": 9,
        "market_quality_score": 63
    },
    {
        "symbol": "SUI-USDT",
        "base": "SUI",
        "name": "Sui",
        "market_cap": 2888756194,
        "rank": 32,
        "coingecko_id": "sui",
        "last_price": "0.7139",
        "volume_24h": "15682423",
        "funding_rate": "0.00010000",
        "spread_percent": 0.02802297884264789,
        "open_interest": "9335401.5264",
        "atr": 0.00790000000000001,
        "atr_percent": 1.1125193634699353,
        "orderbook_depth": 5032411.4983,
        "score_funding": 10,
        "score_spread": 8,
        "score_open_interest": 0,
        "score_atr": 10,
        "score_orderbook_depth": 6,
        "score_data_quality": 3,
        "hard_filter_passed": true,
        "hard_filter_reasons": [],
        "score_market_cap": 8,
        "score_rank": 6,
        "score_volume": 12,
        "market_quality_score": 63
    },
    {
        "symbol": "LINK-USDT",
        "base": "LINK",
        "name": "Chainlink",
        "market_cap": 5518491135,
        "rank": 21,
        "coingecko_id": "chainlink",
        "last_price": "7.376",
        "volume_24h": "1940348.8",
        "funding_rate": "0.00006900",
        "spread_percent": 0.02711496746203606,
        "open_interest": "12025594.352",
        "atr": 0.05585714285714299,
        "atr_percent": 0.749659681346705,
        "orderbook_depth": 1863743.4953,
        "score_funding": 10,
        "score_spread": 8,
        "score_open_interest": 3,
        "score_atr": 7,
        "score_orderbook_depth": 3,
        "score_data_quality": 3,
        "hard_filter_passed": true,
        "hard_filter_reasons": [],
        "score_market_cap": 11,
        "score_rank": 8,
        "score_volume": 6,
        "market_quality_score": 59
    },
    {
        "symbol": "AAVE-USDT",
        "base": "AAVE",
        "name": "Aave",
        "market_cap": 1306259995,
        "rank": 58,
        "coingecko_id": "aave",
        "last_price": "86.01",
        "volume_24h": "572509.8",
        "funding_rate": "-0.00002600",
        "spread_percent": 0.023261223540353593,
        "open_interest": "36090506.12",
        "atr": 1.5807142857142844,
        "atr_percent": 1.6445217287913902,
        "orderbook_depth": 19988780.689999998,
        "score_funding": 10,
        "score_spread": 8,
        "score_open_interest": 6,
        "score_atr": 10,
        "score_orderbook_depth": 6,
        "score_data_quality": 3,
        "hard_filter_passed": true,
        "hard_filter_reasons": [],
        "score_market_cap": 8,
        "score_rank": 4,
        "score_volume": 3,
        "market_quality_score": 58
    },
    {
        "symbol": "LTC-USDT",
        "base": "LTC",
        "name": "Litecoin",
        "market_cap": 3283493553,
        "rank": 27,
        "coingecko_id": "litecoin",
        "last_price": "42.47",
        "volume_24h": "491418.3",
        "funding_rate": "0.00006000",
        "spread_percent": 0.04709206498705704,
        "open_interest": "17480947.08",
        "atr": 0.3478571428571427,
        "atr_percent": 0.8074678339302291,
        "orderbook_depth": 13563531.911,
        "score_funding": 10,
        "score_spread": 5,
        "score_open_interest": 3,
        "score_atr": 7,
        "score_orderbook_depth": 6,
        "score_data_quality": 3,
        "hard_filter_passed": true,
        "hard_filter_reasons": [],
        "score_market_cap": 11,
        "score_rank": 6,
        "score_volume": 3,
        "market_quality_score": 54
    },
    {
        "symbol": "CRO-USDT",
        "base": "CRO",
        "name": "Cronos",
        "market_cap": 2514885523,
        "rank": 36,
        "coingecko_id": "crypto-com-chain",
        "last_price": "0.05458",
        "volume_24h": "43523609.22",
        "funding_rate": "-0.00004200",
        "spread_percent": 0.036650174088325424,
        "open_interest": "933986.50740",
        "atr": 0.00029000000000000006,
        "atr_percent": 0.5218643152780278,
        "orderbook_depth": 47922.8618369,
        "score_funding": 10,
        "score_spread": 5,
        "score_open_interest": 0,
        "score_atr": 7,
        "score_orderbook_depth": 0,
        "score_data_quality": 3,
        "hard_filter_passed": true,
        "hard_filter_reasons": [],
        "score_market_cap": 8,
        "score_rank": 6,
        "score_volume": 12,
        "market_quality_score": 51
    },
    {
        "symbol": "VET-USDT",
        "base": "VET",
        "name": "VeChain",
        "market_cap": 388734356,
        "rank": 119,
        "coingecko_id": "vechain",
        "last_price": "0.004516",
        "volume_24h": "529424977",
        "funding_rate": "0.00010000",
        "spread_percent": 0.04428697962799525,
        "open_interest": "1889501.325595",
        "atr": 7.857142857142847e-05,
        "atr_percent": 1.7581434005689969,
        "orderbook_depth": 103639.85768399999,
        "score_funding": 10,
        "score_spread": 5,
        "score_open_interest": 0,
        "score_atr": 10,
        "score_orderbook_depth": 0,
        "score_data_quality": 3,
        "hard_filter_passed": true,
        "hard_filter_reasons": [],
        "score_market_cap": 5,
        "score_rank": 2,
        "score_volume": 15,
        "market_quality_score": 50
    },
    {
        "symbol": "SUN-USDT",
        "base": "SUN",
        "name": "Sun Token",
        "market_cap": 315852693,
        "rank": 130,
        "coingecko_id": "sun-token",
        "last_price": "0.016417",
        "volume_24h": "140759575",
        "funding_rate": "0.00005000",
        "spread_percent": 0.012182493756462999,
        "open_interest": "1026096.754106",
        "atr": 8.94999999999998e-05,
        "atr_percent": 0.5342964599128399,
        "orderbook_depth": 11578.445587,
        "score_funding": 10,
        "score_spread": 8,
        "score_open_interest": 0,
        "score_atr": 7,
        "score_orderbook_depth": 0,
        "score_data_quality": 3,
        "hard_filter_passed": true,
        "hard_filter_reasons": [],
        "score_market_cap": 5,
        "score_rank": 2,
        "score_volume": 15,
        "market_quality_score": 50
    },
    {
        "symbol": "LUNC-USDT",
        "base": "LUNC",
        "name": "Terra Luna Classic",
        "market_cap": 335322500,
        "rank": 126,
        "coingecko_id": "terra-luna",
        "last_price": "0.00006069",
        "volume_24h": "19405350572",
        "funding_rate": "0.00025600",
        "spread_percent": 0.04944783253667054,
        "open_interest": "985942.92237081",
        "atr": 6.242857142857124e-07,
        "atr_percent": 1.0012601672585604,
        "orderbook_depth": 82403.27911493,
        "score_funding": 8,
        "score_spread": 5,
        "score_open_interest": 0,
        "score_atr": 10,
        "score_orderbook_depth": 0,
        "score_data_quality": 3,
        "hard_filter_passed": true,
        "hard_filter_reasons": [],
        "score_market_cap": 5,
        "score_rank": 2,
        "score_volume": 15,
        "market_quality_score": 48
    },
    {
        "symbol": "JTO-USDT",
        "base": "JTO",
        "name": "Jito",
        "market_cap": 382824198,
        "rank": 121,
        "coingecko_id": "jito-governance-token",
        "last_price": "0.7819",
        "volume_24h": "8944919.190",
        "funding_rate": "0.00005000",
        "spread_percent": 0.03842705264507212,
        "open_interest": "5889899.8793",
        "atr": 0.01869285714285716,
        "atr_percent": 2.301225796239956,
        "orderbook_depth": 58802.19571,
        "score_funding": 10,
        "score_spread": 5,
        "score_open_interest": 0,
        "score_atr": 10,
        "score_orderbook_depth": 0,
        "score_data_quality": 3,
        "hard_filter_passed": true,
        "hard_filter_reasons": [],
        "score_market_cap": 5,
        "score_rank": 2,
        "score_volume": 9,
        "market_quality_score": 44
    },
    {
        "symbol": "ETC-USDT",
        "base": "ETC",
        "name": "Ethereum Classic",
        "market_cap": 1093008702,
        "rank": 63,
        "coingecko_id": "ethereum-classic",
        "last_price": "6.977",
        "volume_24h": "1177927.45",
        "funding_rate": "0.00000200",
        "spread_percent": 0.04298610116062636,
        "open_interest": "6920792.578",
        "atr": 0.06500000000000002,
        "atr_percent": 0.894331315354981,
        "orderbook_depth": 299097.17111,
        "score_funding": 10,
        "score_spread": 5,
        "score_open_interest": 0,
        "score_atr": 7,
        "score_orderbook_depth": 0,
        "score_data_quality": 3,
        "hard_filter_passed": true,
        "hard_filter_reasons": [],
        "score_market_cap": 8,
        "score_rank": 4,
        "score_volume": 6,
        "market_quality_score": 43
    },
    {
        "symbol": "CAKE-USDT",
        "base": "CAKE",
        "name": "PancakeSwap",
        "market_cap": 435382709,
        "rank": 111,
        "coingecko_id": "pancakeswap-token",
        "last_price": "1.3443",
        "volume_24h": "1788781.400",
        "funding_rate": "0.00005000",
        "spread_percent": 0.014896469536718158,
        "open_interest": "2003934.9885",
        "atr": 0.010999999999999979,
        "atr_percent": 0.8206505520740062,
        "orderbook_depth": 246511.13016220002,
        "score_funding": 10,
        "score_spread": 8,
        "score_open_interest": 0,
        "score_atr": 7,
        "score_orderbook_depth": 0,
        "score_data_quality": 3,
        "hard_filter_passed": true,
        "hard_filter_reasons": [],
        "score_market_cap": 5,
        "score_rank": 2,
        "score_volume": 6,
        "market_quality_score": 41
    }
]